shipyard_snowflake/__init__.py
shipyard_snowflake/snowflake.py
shipyard_snowflake/snowpark.py
shipyard_snowflake/cli/__init__.py
shipyard_snowflake/cli/authtest.py
shipyard_snowflake/cli/execute_sql.py
shipyard_snowflake/cli/fetch.py
shipyard_snowflake/cli/upload.py
shipyard_snowflake/utils/exceptions.py
shipyard_snowflake/utils/utils.py
shipyard_snowflake-0.3.1.dist-info/METADATA
shipyard_snowflake-0.3.1.dist-info/WHEEL
shipyard_snowflake-0.3.1.dist-info/top_level.txt
shipyard_snowflake-0.3.1.dist-info/RECORD
