Metadata-Version: 2.4
Name: shipyard-snowflake
Version: 0.3.1
Summary: A local client for conecting and working with Snowflake
Requires-Python: >=3.11
Requires-Dist: dask>=2025.3.0
Requires-Dist: pandas>=2.2.3
Requires-Dist: psutil>=7.0.0
Requires-Dist: pyarrow<19.0.0
Requires-Dist: shipyard-bp-utils>=1.3.2
Requires-Dist: shipyard-templates>=0.9.0
Requires-Dist: snowflake-connector-python>=3.14.0
Requires-Dist: snowflake-snowpark-python>=1.30.0
